SecretManagerCredentials/SecretManagerFetcher.py
SecretManagerCredentials/__init__.py
SecretManagerCredentials-0.0.6.dist-info/Licence
SecretManagerCredentials-0.0.6.dist-info/METADATA
SecretManagerCredentials-0.0.6.dist-info/WHEEL
SecretManagerCredentials-0.0.6.dist-info/top_level.txt
SecretManagerCredentials-0.0.6.dist-info/RECORD
