Metadata-Version: 2.1
Name: SecretManagerCredentials
Version: 0.0.6
Summary: Convenient wrapper for executing codes on AWS for connecting and fetching credentials from vault
Home-page: 
Download-URL: 
Author: Mallikarjuna Devaraya
License: MIT
Keywords: Vault Credential Fetch,Credential Fetch,Vault
Classifier: Development Status :: 4 - Beta
Classifier: Intended Audience :: Developers
Classifier: Topic :: Software Development :: Build Tools
Classifier: License :: OSI Approved :: MIT License
Classifier: Programming Language :: Python :: 3.8
License-File: Licence
Requires-Dist: hvac (==0.11.2)
Requires-Dist: boto3 (==1.18.63)
Requires-Dist: botocore (==1.21.65)
